fish_async_task/__init__.py
fish_async_task/cleanup.py
fish_async_task/config.py
fish_async_task/py.typed
fish_async_task/task_manager.py
fish_async_task/task_status.py
fish_async_task/types.py
fish_async_task/worker.py
fish_async_task-0.2.2.dist-info/licenses/LICENSE
fish_async_task-0.2.2.dist-info/METADATA
fish_async_task-0.2.2.dist-info/WHEEL
fish_async_task-0.2.2.dist-info/top_level.txt
fish_async_task-0.2.2.dist-info/RECORD
