Metadata-Version: 2.4
Name: fish-async-task
Version: 0.2.2
Summary: 纯Python实现的异步任务管理器，支持线程池和动态伸缩
Author: fishzjp
License-Expression: MIT
Project-URL: Homepage, https://github.com/fishzjp/FishAsyncTask
Project-URL: Documentation, https://github.com/fishzjp/FishAsyncTask#readme
Project-URL: Repository, https://github.com/fishzjp/FishAsyncTask
Project-URL: Issues, https://github.com/fishzjp/FishAsyncTask/issues
Keywords: async,task,manager,threadpool,queue
Classifier: Development Status :: 4 - Beta
Classifier: Intended Audience :: Developers
Classifier: Programming Language :: Python :: 3
Classifier: Programming Language :: Python :: 3.9
Classifier: Programming Language :: Python :: 3.10
Classifier: Programming Language :: Python :: 3.11
Classifier: Programming Language :: Python :: 3.12
Classifier: Topic :: Software Development :: Libraries :: Python Modules
Classifier: Topic :: System :: Distributed Computing
Requires-Python: >=3.9
License-File: LICENSE
Provides-Extra: performance
Requires-Dist: psutil>=5.9.0; extra == "performance"
Requires-Dist: redis>=4.5.0; extra == "performance"
Requires-Dist: huey>=2.4.0; extra == "performance"
Requires-Dist: dramatiq>=1.14.0; extra == "performance"
Provides-Extra: dev
Requires-Dist: pytest>=7.0.0; extra == "dev"
Requires-Dist: pytest-cov>=4.0.0; extra == "dev"
Requires-Dist: pytest-benchmark>=4.0.0; extra == "dev"
Requires-Dist: locust>=2.0.0; extra == "dev"
Requires-Dist: black>=23.0.0; extra == "dev"
Requires-Dist: isort>=5.0.0; extra == "dev"
Requires-Dist: mypy>=1.0.0; extra == "dev"
Requires-Dist: lxml>=4.9.0; extra == "dev"
Requires-Dist: interrogate>=1.5.0; extra == "dev"
Dynamic: license-file
